iptv9.py
iptv9-0.1.1.dist-info/METADATA
iptv9-0.1.1.dist-info/WHEEL
iptv9-0.1.1.dist-info/entry_points.txt
iptv9-0.1.1.dist-info/top_level.txt
iptv9-0.1.1.dist-info/RECORD
