Metadata-Version: 2.4
Name: iptv9
Version: 0.1.1
Summary: Web Enumeration Tool
Author: ssskingsss12
Author-email: smalls3000i@gmail.com
Classifier: Programming Language :: Python :: 3
Requires-Python: >=3.12
Dynamic: author
Dynamic: author-email
Dynamic: classifier
Dynamic: description
Dynamic: description-content-type
Dynamic: requires-python
Dynamic: summary
